handshake/__init__.py
handshake/api.py
skunkworks_repo-1.0.2.dist-info/LICENSE
skunkworks_repo-1.0.2.dist-info/METADATA
skunkworks_repo-1.0.2.dist-info/WHEEL
skunkworks_repo-1.0.2.dist-info/top_level.txt
skunkworks_repo-1.0.2.dist-info/RECORD
