Metadata-Version: 2.1
Name: skunkworks-repo
Version: 1.0.2
Summary: The Skunk Works Code Repository
Home-page: https://github.com/skunk-ink/skunkworks
Author: skunk-ink
Author-email: UNKNOWN
License: MIT
Download-URL: https://github.com/skunk-ink/skunkworks/archive/refs/tags/v1.0.2.tar.gz
Keywords: Handshake,API,HNS
Platform: UNKNOWN
Classifier: Intended Audience :: Developers
Classifier: Topic :: Software Development :: Build Tools
Classifier: License :: OSI Approved :: MIT License
Classifier: Programming Language :: Python :: 3
Classifier: Programming Language :: Python :: 3.4
Classifier: Programming Language :: Python :: 3.5
Requires-Dist: json
Requires-Dist: requests
